easygrpc/__init__.py
easygrpc/action.py
easygrpc/exceptions.py
easygrpc/start.py
easygrpc/state.py
example/__init__.py
example/client.py
example/helloworld_action.py
example/helloworld_grpc.py
example/helloworld_pb2.py
easy_grpc-0.0.1b5.dist-info/LICENSE.md
easy_grpc-0.0.1b5.dist-info/METADATA
easy_grpc-0.0.1b5.dist-info/WHEEL
easy_grpc-0.0.1b5.dist-info/top_level.txt
easy_grpc-0.0.1b5.dist-info/RECORD
