Metadata-Version: 2.1
Name: easy-grpc
Version: 0.0.1b5
Summary: Helper module to build GRPC service easily
Home-page: https://gitlab.com/ist-supsi/istsosm/utils/easygrpc
Author: IST-SUPSI
Author-email: geoservice@supsi.ch
License: UNKNOWN
Project-URL: Documentation, https://gitlab.com/ist-supsi/istsosm/utils/easygrpc
Project-URL: Source, https://gitlab.com/ist-supsi/istsosm/utils/easygrpc
Project-URL: Tracker, https://gitlab.com/ist-supsi/istsosm/utils/easygrpc/issues
Keywords: istsos grpc
Platform: UNKNOWN
Classifier: Development Status :: 4 - Beta
Classifier: Intended Audience :: Developers
Classifier: Programming Language :: Python :: 3 :: Only
Requires-Python: >=3, <4
Requires-Dist: googleapis-common-protos
Requires-Dist: grpclib
Requires-Dist: asyncpg
